pydelta/__init__.py
pydelta/checker.py
pydelta/cli.py
pydelta/manager.py
pydelta/mutator.py
pydelta/mutator_options.py
pydelta/mutators_arithmetic.py
pydelta/mutators_bitvectors.py
pydelta/mutators_boolean.py
pydelta/mutators_core.py
pydelta/mutators_smtlib.py
pydelta/mutators_strings.py
pydelta/options.py
pydelta/parser.py
pydelta/semantics.py
pydelta/version.py
pydelta/tests/__init__.py
pydelta/tests/test_parser.py
pydelta_smt-0.3.data/scripts/pydelta
pydelta_smt-0.3.dist-info/LICENSE
pydelta_smt-0.3.dist-info/METADATA
pydelta_smt-0.3.dist-info/WHEEL
pydelta_smt-0.3.dist-info/top_level.txt
pydelta_smt-0.3.dist-info/RECORD
