Metadata-Version: 2.1
Name: pydelta-smt
Version: 0.3
Summary: Delta debugger for SMT-LIB files
Home-page: https://github.com/nafur/pydelta
Author: Gereon Kremer
Author-email: gereon.kremer@gmail.com
License: MIT
Download-URL: https://github.com/nafur/pydelta
Project-URL: Bug Tracker, https://github.com/nafur/pydelta/issues
Project-URL: Documentation, https://pydelta.readthedocs.io/
Project-URL: Source Code, https://github.com/nafur/pydelta
Platform: UNKNOWN
Classifier: Intended Audience :: Science/Research
Classifier: License :: OSI Approved :: MIT License
Classifier: Programming Language :: Python :: 3.5
Classifier: Programming Language :: Python :: 3.6
Classifier: Programming Language :: Python :: 3.7
Classifier: Programming Language :: Python :: 3.8
Classifier: Programming Language :: Python :: 3.9
Requires-Python: >=3.5
Requires-Dist: progressbar (>=2.5)
Requires-Dist: sphinx-rtd-theme (>=0.4.3)
Requires-Dist: importlib-metadata (>=1.7) ; python_version < "3.8"
